JesseReportDiscord/__init__.py
JesseReportDiscord/sendJesseReportToDiscord.py
JesseReportDiscord-1.0.4.dist-info/LICENSE.txt
JesseReportDiscord-1.0.4.dist-info/METADATA
JesseReportDiscord-1.0.4.dist-info/WHEEL
JesseReportDiscord-1.0.4.dist-info/top_level.txt
JesseReportDiscord-1.0.4.dist-info/RECORD
